{
  "indexes": [
    {
      "collectionGroup": "team_workouts",
      "queryScope": "COLLECTION",
      "fields": [
        { "fieldPath": "recordType", "order": "ASCENDING" },
        { "fieldPath": "startTimestamp", "order": "ASCENDING" }
      ]
    },
    {
      "collectionGroup": "team_workouts",
      "queryScope": "COLLECTION",
      "fields": [
        { "fieldPath": "teamId", "order": "ASCENDING" },
        { "fieldPath": "startTimestamp", "order": "ASCENDING" }
      ]
    },
    {
      "collectionGroup": "match_results_public",
      "queryScope": "COLLECTION",
      "fields": [
        { "fieldPath": "tenantId", "order": "ASCENDING" },
        { "fieldPath": "playerEmails", "arrayConfig": "CONTAINS" },
        { "fieldPath": "recordedAt", "order": "DESCENDING" }
      ]
    },
    {
      "collectionGroup": "assignments",
      "queryScope": "COLLECTION",
      "fields": [
        { "fieldPath": "playerId", "order": "ASCENDING" },
        { "fieldPath": "status", "order": "ASCENDING" }
      ]
    },
    {
      "collectionGroup": "assignments",
      "queryScope": "COLLECTION",
      "fields": [
        { "fieldPath": "teamId", "order": "ASCENDING" },
        { "fieldPath": "status", "order": "ASCENDING" },
        { "fieldPath": "completedAt", "order": "DESCENDING" }
      ]
    },
    {
      "collectionGroup": "player_stats",
      "queryScope": "COLLECTION",
      "fields": [
        { "fieldPath": "teamId", "order": "ASCENDING" },
        { "fieldPath": "xp_this_week", "order": "DESCENDING" }
      ]
    },
    {
      "collectionGroup": "users",
      "queryScope": "COLLECTION",
      "fields": [
        { "fieldPath": "teamId", "order": "ASCENDING" },
        { "fieldPath": "xp", "order": "DESCENDING" }
      ]
    },
    {
      "collectionGroup": "minor_retention_queue",
      "queryScope": "COLLECTION",
      "fields": [
        { "fieldPath": "playerEmail", "order": "ASCENDING" },
        { "fieldPath": "status", "order": "ASCENDING" }
      ]
    },
    {
      "collectionGroup": "minor_retention_queue",
      "queryScope": "COLLECTION",
      "fields": [
        { "fieldPath": "status", "order": "ASCENDING" },
        { "fieldPath": "expireAt", "order": "ASCENDING" }
      ]
    },
    {
      "collectionGroup": "reps",
      "queryScope": "COLLECTION",
      "fields": [
        { "fieldPath": "player", "order": "ASCENDING" },
        { "fieldPath": "teamId", "order": "ASCENDING" }
      ]
    },
    {
      "collectionGroup": "vpc_requests",
      "queryScope": "COLLECTION",
      "fields": [
        { "fieldPath": "clubId", "order": "ASCENDING" },
        { "fieldPath": "status", "order": "ASCENDING" }
      ]
    },
    {
      "collectionGroup": "vpc_requests",
      "queryScope": "COLLECTION",
      "fields": [
        { "fieldPath": "clubId", "order": "ASCENDING" },
        { "fieldPath": "status", "order": "ASCENDING" },
        { "fieldPath": "consentedAt", "order": "DESCENDING" }
      ]
    },
    {
      "collectionGroup": "vpc_requests",
      "queryScope": "COLLECTION",
      "fields": [
        { "fieldPath": "playerEmail", "order": "ASCENDING" },
        { "fieldPath": "status", "order": "ASCENDING" }
      ]
    },
    {
      "collectionGroup": "player_lookup",
      "queryScope": "COLLECTION",
      "fields": [
        { "fieldPath": "teamId", "order": "ASCENDING" },
        { "fieldPath": "playerName", "order": "ASCENDING" }
      ]
    },
    {
      "collectionGroup": "in_app_messages",
      "queryScope": "COLLECTION",
      "fields": [
        { "fieldPath": "toPlayerEmail", "order": "ASCENDING" },
        { "fieldPath": "createdAt", "order": "DESCENDING" }
      ]
    },
    {
      "collectionGroup": "in_app_messages",
      "queryScope": "COLLECTION",
      "fields": [
        { "fieldPath": "ccParentEmails", "arrayConfig": "CONTAINS" },
        { "fieldPath": "createdAt", "order": "DESCENDING" }
      ]
    },
    {
      "collectionGroup": "in_app_messages",
      "queryScope": "COLLECTION",
      "fields": [
        { "fieldPath": "fromEmail", "order": "ASCENDING" },
        { "fieldPath": "createdAt", "order": "DESCENDING" }
      ]
    },
    {
      "collectionGroup": "in_app_messages",
      "queryScope": "COLLECTION",
      "fields": [
        { "fieldPath": "teamClubId", "order": "ASCENDING" },
        { "fieldPath": "createdAt", "order": "DESCENDING" }
      ]
    },
    {
      "collectionGroup": "coach_invites",
      "queryScope": "COLLECTION",
      "fields": [
        { "fieldPath": "clubId", "order": "ASCENDING" },
        { "fieldPath": "status", "order": "ASCENDING" }
      ]
    },
    {
      "collectionGroup": "coach_invites",
      "queryScope": "COLLECTION",
      "fields": [
        { "fieldPath": "clubId", "order": "ASCENDING" },
        { "fieldPath": "status", "order": "ASCENDING" },
        { "fieldPath": "createdAt", "order": "DESCENDING" }
      ]
    },
    {
      "collectionGroup": "coach_invites",
      "queryScope": "COLLECTION",
      "fields": [
        { "fieldPath": "coachEmail", "order": "ASCENDING" },
        { "fieldPath": "status", "order": "ASCENDING" },
        { "fieldPath": "createdAt", "order": "ASCENDING" }
      ]
    },
    {
      "collectionGroup": "coach_invites",
      "queryScope": "COLLECTION",
      "fields": [
        { "fieldPath": "status", "order": "ASCENDING" },
        { "fieldPath": "createdAt", "order": "ASCENDING" }
      ]
    },
    {
      "collectionGroup": "public_player_profiles",
      "queryScope": "COLLECTION",
      "fields": [
        { "fieldPath": "clubId", "order": "ASCENDING" },
        { "fieldPath": "current_level", "order": "DESCENDING" }
      ]
    },
    {
      "collectionGroup": "public_player_profiles",
      "queryScope": "COLLECTION",
      "fields": [
        { "fieldPath": "ageGroup", "order": "ASCENDING" },
        { "fieldPath": "current_level", "order": "DESCENDING" }
      ]
    },
    {
      "collectionGroup": "public_player_profiles",
      "queryScope": "COLLECTION",
      "fields": [
        { "fieldPath": "position", "order": "ASCENDING" },
        { "fieldPath": "current_level", "order": "DESCENDING" }
      ]
    },
    {
      "collectionGroup": "public_player_profiles",
      "queryScope": "COLLECTION",
      "fields": [
        { "fieldPath": "ageGroup", "order": "ASCENDING" },
        { "fieldPath": "position", "order": "ASCENDING" },
        { "fieldPath": "current_level", "order": "DESCENDING" }
      ]
    },
    {
      "collectionGroup": "users",
      "queryScope": "COLLECTION",
      "fields": [
        { "fieldPath": "teamId", "order": "ASCENDING" },
        { "fieldPath": "playerName", "order": "ASCENDING" }
      ]
    },
    {
      "collectionGroup": "users",
      "queryScope": "COLLECTION",
      "fields": [
        { "fieldPath": "teamId", "order": "ASCENDING" },
        { "fieldPath": "role", "order": "ASCENDING" }
      ]
    },
    {
      "collectionGroup": "trial_scores",
      "queryScope": "COLLECTION",
      "fields": [
        { "fieldPath": "teamId", "order": "ASCENDING" },
        { "fieldPath": "status", "order": "ASCENDING" },
        { "fieldPath": "submittedAt", "order": "DESCENDING" }
      ]
    },
    {
      "collectionGroup": "trial_scores",
      "queryScope": "COLLECTION",
      "fields": [
        { "fieldPath": "playerId", "order": "ASCENDING" },
        { "fieldPath": "status", "order": "ASCENDING" },
        { "fieldPath": "verifiedAt", "order": "DESCENDING" }
      ]
    },
    {
      "collectionGroup": "assigned_missions",
      "queryScope": "COLLECTION",
      "fields": [
        { "fieldPath": "targetPlayerKey", "order": "ASCENDING" },
        { "fieldPath": "status", "order": "ASCENDING" }
      ]
    },
    {
      "collectionGroup": "operative_dispatches",
      "queryScope": "COLLECTION",
      "fields": [
        { "fieldPath": "childEmail", "order": "ASCENDING" },
        { "fieldPath": "dispatchCode", "order": "ASCENDING" }
      ]
    },
    {
      "collectionGroup": "deployment_calendar_entries",
      "queryScope": "COLLECTION",
      "fields": [
        { "fieldPath": "clubId", "order": "ASCENDING" },
        { "fieldPath": "startsAt", "order": "DESCENDING" }
      ]
    },
    {
      "collectionGroup": "users",
      "queryScope": "COLLECTION",
      "fields": [
        { "fieldPath": "role", "order": "ASCENDING" },
        { "fieldPath": "email", "order": "ASCENDING" }
      ]
    },
    {
      "collectionGroup": "telemetry_events",
      "queryScope": "COLLECTION_GROUP",
      "fields": [
        { "fieldPath": "matchId", "order": "ASCENDING" },
        { "fieldPath": "timestamp", "order": "DESCENDING" }
      ]
    },
    {
      "collectionGroup": "team_assignments",
      "queryScope": "COLLECTION",
      "fields": [
        { "fieldPath": "teamId", "order": "ASCENDING" },
        { "fieldPath": "createdAt", "order": "DESCENDING" }
      ]
    },
    {
      "collectionGroup": "global_drills",
      "queryScope": "COLLECTION",
      "fields": [
        { "fieldPath": "attributeId", "order": "ASCENDING" },
        { "fieldPath": "tier", "order": "ASCENDING" }
      ]
    },
    {
      "collectionGroup": "drill_completions",
      "queryScope": "COLLECTION",
      "fields": [
        { "fieldPath": "playerUid", "order": "ASCENDING" },
        { "fieldPath": "loggedAt", "order": "DESCENDING" }
      ]
    },
    {
      "collectionGroup": "drill_completions",
      "queryScope": "COLLECTION",
      "fields": [
        { "fieldPath": "playerUid", "order": "ASCENDING" },
        { "fieldPath": "attributeId", "order": "ASCENDING" },
        { "fieldPath": "loggedAt", "order": "ASCENDING" }
      ]
    },
    {
      "collectionGroup": "grit_awards",
      "queryScope": "COLLECTION",
      "fields": [
        { "fieldPath": "playerUid", "order": "ASCENDING" },
        { "fieldPath": "loggedAt", "order": "DESCENDING" }
      ]
    },
    {
      "collectionGroup": "bounties",
      "queryScope": "COLLECTION",
      "fields": [
        { "fieldPath": "householdId", "order": "ASCENDING" },
        { "fieldPath": "status", "order": "ASCENDING" },
        { "fieldPath": "createdAt", "order": "DESCENDING" }
      ]
    },
    {
      "collectionGroup": "bounties",
      "queryScope": "COLLECTION",
      "fields": [
        { "fieldPath": "playerEmail", "order": "ASCENDING" },
        { "fieldPath": "status", "order": "ASCENDING" }
      ]
    },
    {
      "collectionGroup": "bounties",
      "queryScope": "COLLECTION",
      "fields": [
        { "fieldPath": "playerEmail", "order": "ASCENDING" },
        { "fieldPath": "status", "order": "ASCENDING" },
        { "fieldPath": "expiresAt", "order": "ASCENDING" }
      ]
    },
    {
      "collectionGroup": "bounty_audit",
      "queryScope": "COLLECTION",
      "fields": [
        { "fieldPath": "bountyId", "order": "ASCENDING" },
        { "fieldPath": "occurredAt", "order": "DESCENDING" }
      ]
    },
    {
      "collectionGroup": "telemetry_boosts",
      "queryScope": "COLLECTION_GROUP",
      "fields": [
        { "fieldPath": "playerEmail", "order": "ASCENDING" },
        { "fieldPath": "expiresAt", "order": "ASCENDING" }
      ]
    },
    {
      "collectionGroup": "reengagement_alerts",
      "queryScope": "COLLECTION",
      "fields": [
        { "fieldPath": "uid", "order": "ASCENDING" },
        { "fieldPath": "acknowledgedAt", "order": "ASCENDING" },
        { "fieldPath": "scheduledFor", "order": "DESCENDING" }
      ]
    },
    {
      "collectionGroup": "memory_capsules",
      "queryScope": "COLLECTION_GROUP",
      "fields": [
        { "fieldPath": "acknowledged", "order": "ASCENDING" },
        { "fieldPath": "surfacedAt", "order": "DESCENDING" }
      ]
    },
    {
      "collectionGroup": "team_assignments",
      "queryScope": "COLLECTION",
      "fields": [
        { "fieldPath": "teamId", "order": "ASCENDING" },
        { "fieldPath": "status", "order": "ASCENDING" },
        { "fieldPath": "priority", "order": "ASCENDING" }
      ]
    },
    {
      "collectionGroup": "team_assignments",
      "queryScope": "COLLECTION",
      "fields": [
        { "fieldPath": "teamId", "order": "ASCENDING" },
        { "fieldPath": "tenantId", "order": "ASCENDING" },
        { "fieldPath": "status", "order": "ASCENDING" },
        { "fieldPath": "priority", "order": "ASCENDING" }
      ]
    },
    {
      "collectionGroup": "team_assignments",
      "queryScope": "COLLECTION",
      "fields": [
        { "fieldPath": "teamId", "order": "ASCENDING" },
        { "fieldPath": "status", "order": "ASCENDING" },
        { "fieldPath": "expiresAt", "order": "ASCENDING" }
      ]
    },
    {
      "collectionGroup": "team_assignments",
      "queryScope": "COLLECTION",
      "fields": [
        { "fieldPath": "targetUids", "arrayConfig": "CONTAINS" },
        { "fieldPath": "status", "order": "ASCENDING" },
        { "fieldPath": "priority", "order": "ASCENDING" }
      ]
    },
    {
      "collectionGroup": "team_assignments",
      "queryScope": "COLLECTION",
      "fields": [
        { "fieldPath": "teamId", "order": "ASCENDING" },
        { "fieldPath": "tenantId", "order": "ASCENDING" },
        { "fieldPath": "assignedByUid", "order": "ASCENDING" },
        { "fieldPath": "clientDeployId", "order": "ASCENDING" }
      ]
    },
    {
      "collectionGroup": "team_broadcasts",
      "queryScope": "COLLECTION",
      "fields": [
        { "fieldPath": "teamId", "order": "ASCENDING" },
        { "fieldPath": "createdAt", "order": "DESCENDING" }
      ]
    },
    {
      "collectionGroup": "team_broadcasts",
      "queryScope": "COLLECTION",
      "fields": [
        { "fieldPath": "ccParentEmails", "arrayConfig": "CONTAINS" },
        { "fieldPath": "createdAt", "order": "DESCENDING" }
      ]
    },
    {
      "collectionGroup": "team_broadcasts",
      "queryScope": "COLLECTION",
      "fields": [
        { "fieldPath": "parentRecipientEmails", "arrayConfig": "CONTAINS" },
        { "fieldPath": "createdAt", "order": "DESCENDING" }
      ]
    },
    {
      "collectionGroup": "broadcast_acknowledgements",
      "queryScope": "COLLECTION",
      "fields": [
        { "fieldPath": "messageId", "order": "ASCENDING" },
        { "fieldPath": "acknowledgedAt", "order": "DESCENDING" }
      ]
    },
    {
      "collectionGroup": "audit_logs",
      "queryScope": "COLLECTION",
      "fields": [
        { "fieldPath": "tenantId", "order": "ASCENDING" },
        { "fieldPath": "timestamp", "order": "DESCENDING" }
      ]
    },
    {
      "collectionGroup": "completion_verifications",
      "queryScope": "COLLECTION",
      "fields": [
        { "fieldPath": "householdId", "order": "ASCENDING" },
        { "fieldPath": "status", "order": "ASCENDING" },
        { "fieldPath": "createdAt", "order": "DESCENDING" }
      ]
    },
    {
      "collectionGroup": "message_incidents",
      "queryScope": "COLLECTION",
      "fields": [
        { "fieldPath": "clubId", "order": "ASCENDING" },
        { "fieldPath": "createdAt", "order": "DESCENDING" }
      ]
    },
    {
      "collectionGroup": "season_registrations",
      "queryScope": "COLLECTION",
      "fields": [
        { "fieldPath": "tenantId", "order": "ASCENDING" },
        { "fieldPath": "seasonId", "order": "ASCENDING" },
        { "fieldPath": "paymentStatus", "order": "ASCENDING" }
      ]
    },
    {
      "collectionGroup": "messages",
      "queryScope": "COLLECTION",
      "fields": [
        { "fieldPath": "householdId", "order": "ASCENDING" },
        { "fieldPath": "createdAt", "order": "DESCENDING" }
      ]
    },
    {
      "collectionGroup": "messages",
      "queryScope": "COLLECTION",
      "fields": [
        { "fieldPath": "guardianEmail", "order": "ASCENDING" },
        { "fieldPath": "createdAt", "order": "DESCENDING" }
      ]
    }
  ],
  "fieldOverrides": [
    {
      "collectionGroup": "xpHistory",
      "fieldPath": "date",
      "indexes": [
        {
          "order": "ASCENDING",
          "queryScope": "COLLECTION_GROUP"
        }
      ]
    },
    {
      "collectionGroup": "trajectory_months",
      "fieldPath": "monthKey",
      "indexes": [
        {
          "order": "DESCENDING",
          "queryScope": "COLLECTION_GROUP"
        }
      ]
    },
    {
      "collectionGroup": "users",
      "fieldPath": "lastActiveAt",
      "indexes": [
        {
          "order": "ASCENDING",
          "queryScope": "COLLECTION"
        }
      ]
    }
  ]
}
